jds6600/__init__.py
jds6600/cli.py
jds6600/core.py
jds6600-1.1.1.dist-info/entry_points.txt
jds6600-1.1.1.dist-info/WHEEL
jds6600-1.1.1.dist-info/METADATA
jds6600-1.1.1.dist-info/RECORD
