Metadata-Version: 2.1
Name: jds6600
Version: 1.1.1
Summary: A Python package form the JDS6600 DDS Signal Generator/Counter
Author-email: Wim De Hul <wim@dehul.net>
Requires-Python: >=3.7
Classifier: Programming Language :: Python :: 3
Classifier: License :: OSI Approved :: MIT License
Classifier: Operating System :: OS Independent
Requires-Dist: pyserial==3.5
Requires-Dist: pytest==7.1.3 ; extra == "test"
Requires-Dist: mypy==0.982 ; extra == "test"
Requires-Dist: black==22.10.0 ; extra == "test"
Requires-Dist: flake8==5.0.4 ; extra == "test"
Project-URL: Bug Tracker, https://github.com/WimDH/JDS6600/issues
Project-URL: Homepage, https://github.com/WimDH/JDS6600
Provides-Extra: test
